rpa_hub/__init__.py
rpa_hub/auth.py
rpa_hub/send_log.py
rpa_hub-0.3.0.dist-info/METADATA
rpa_hub-0.3.0.dist-info/WHEEL
rpa_hub-0.3.0.dist-info/top_level.txt
rpa_hub-0.3.0.dist-info/RECORD
